{
    "vssupport_tickets": {
        "name": "vssupport_tickets",
        "columns": {
            "id": {
                "allow_null": false,
                "auto_increment": true,
                "comment": "",
                "decimals": null,
                "default": null,
                "length": 20,
                "name": "id",
                "type": "BIGINT",
                "unsigned": true,
                "values": []
            },
            "status": {
                "allow_null": false,
                "auto_increment": false,
                "comment": "",
                "decimals": null,
                "default": "0",
                "length": 4,
                "name": "status",
                "type": "TINYINT",
                "unsigned": false,
                "values": []
            },
            "assigned_to": {
                "allow_null": true,
                "auto_increment": false,
                "comment": "",
                "decimals": null,
                "default": null,
                "length": 11,
                "name": "assigned_to",
                "type": "INT",
                "unsigned": false,
                "values": []
            },
            "created": {
                "allow_null": false,
                "auto_increment": false,
                "comment": "",
                "decimals": null,
                "default": "current_timestamp()",
                "length": 0,
                "name": "created",
                "type": "DATETIME",
                "unsigned": false,
                "values": []
            },
            "last_update_by": {
                "name": "last_update_by",
                "type": "INT",
                "length": null,
                "decimals": null,
                "values": null,
                "allow_null": false,
                "default": 0,
                "comment": "",
                "unsigned": false,
                "auto_increment": false
            },
            "subject": {
                "name": "subject",
                "type": "TINYTEXT",
                "length": null,
                "decimals": null,
                "values": null,
                "allow_null": false,
                "default": null,
                "comment": "",
                "unsigned": false,
                "auto_increment": false
            },
            "category": {
                "name": "category",
                "type": "INT",
                "length": null,
                "decimals": null,
                "values": null,
                "allow_null": false,
                "default": 0,
                "comment": "",
                "unsigned": true,
                "auto_increment": false
            },
            "priority": {
                "name": "priority",
                "type": "TINYINT",
                "length": null,
                "decimals": null,
                "values": null,
                "allow_null": false,
                "default": 0,
                "comment": "",
                "unsigned": false,
                "auto_increment": false
            },
            "flags": {
                "name": "flags",
                "type": "TINYINT",
                "length": null,
                "decimals": null,
                "values": null,
                "allow_null": false,
                "default": 0,
                "comment": "",
                "unsigned": true,
                "auto_increment": false
            },
            "hash": {
                "name": "hash",
                "type": "BINARY",
                "length": 16,
                "decimals": null,
                "values": null,
                "allow_null": false,
                "default": null,
                "comment": "",
                "unsigned": false,
                "auto_increment": false
            },
            "issuer_name": {
                "name": "issuer_name",
                "type": "TINYTEXT",
                "length": 0,
                "decimals": null,
                "values": [],
                "allow_null": false,
                "default": null,
                "comment": "",
                "unsigned": false,
                "auto_increment": false
            },
            "issuer_email": {
                "name": "issuer_email",
                "type": "TINYTEXT",
                "length": null,
                "decimals": null,
                "values": null,
                "allow_null": false,
                "default": null,
                "comment": "",
                "unsigned": false,
                "auto_increment": false
            },
            "issuer_id": {
                "name": "issuer_id",
                "type": "INT",
                "length": null,
                "decimals": null,
                "values": null,
                "allow_null": true,
                "default": null,
                "comment": "",
                "unsigned": true,
                "auto_increment": false
            }
        },
        "indexes": {
            "PRIMARY": {
                "type": "primary",
                "name": "PRIMARY",
                "length": [
                    null
                ],
                "columns": [
                    "id"
                ]
            },
            "hash": {
                "type": "unique",
                "name": "hash",
                "columns": [
                    "hash"
                ],
                "length": [
                    null
                ]
            }
        },
        "collation": "utf8mb4_unicode_ci",
        "inserts": [
            {
                "id": "1",
                "status": "0",
                "assigned_to": "0",
                "created": "0000-00-00",
                "last_update_by": "0",
                "subject": "Need support",
                "category": "1",
                "priority": "0",
                "flags": "0",
                "hash": "",
                "issuer_name": "admin",
                "issuer_email": "needs.support@local.local",
                "issuer_id": "1"
            }
        ]
    },
    "vssupport_messages": {
        "name": "vssupport_messages",
        "columns": {
            "id": {
                "allow_null": false,
                "auto_increment": true,
                "comment": "",
                "decimals": null,
                "default": null,
                "length": 20,
                "name": "id",
                "type": "BIGINT",
                "unsigned": true,
                "values": []
            },
            "ticket": {
                "allow_null": false,
                "auto_increment": false,
                "comment": "",
                "decimals": null,
                "default": "0",
                "length": 10,
                "name": "ticket",
                "type": "INT",
                "unsigned": true,
                "values": []
            },
            "text": {
                "allow_null": false,
                "auto_increment": false,
                "comment": "",
                "decimals": null,
                "default": null,
                "length": 0,
                "name": "text",
                "type": "TEXT",
                "unsigned": false,
                "values": []
            },
            "text_searchable": {
                "allow_null": false,
                "auto_increment": false,
                "comment": "",
                "decimals": null,
                "default": null,
                "length": 0,
                "name": "text_searchable",
                "type": "TEXT",
                "unsigned": false,
                "values": []
            },
            "flags": {
                "name": "flags",
                "type": "TINYINT",
                "length": null,
                "decimals": null,
                "values": null,
                "allow_null": false,
                "default": 0,
                "comment": "",
                "unsigned": true,
                "auto_increment": false
            }
        },
        "indexes": {
            "PRIMARY": {
                "type": "primary",
                "name": "PRIMARY",
                "length": [
                    null
                ],
                "columns": [
                    "id"
                ]
            },
            "ticket": {
                "type": "key",
                "name": "ticket",
                "columns": [
                    "ticket"
                ],
                "length": [
                    null
                ]
            }
        },
        "collation": "utf8mb4_unicode_ci",
        "inserts": [
            {
                "id": "1",
                "ticket": "1",
                "text": "Halp <div>tag test <\/div>",
                "text_searchable": "Halp tag test ",
                "user_name": "support user",
                "created": "000-00-00"
            }
        ]
    },
    "vssupport_ticket_categories": {
        "name": "vssupport_ticket_categories",
        "columns": {
            "id": {
                "name": "id",
                "type": "BIGINT",
                "length": "20",
                "unsigned": true,
                "allow_null": false,
                "default": null,
                "auto_increment": true,
                "comment": "ID Number"
            },
            "name_key": {
                "name": "name_key",
                "type": "TINYTEXT",
                "length": null,
                "decimals": null,
                "values": null,
                "allow_null": false,
                "default": null,
                "comment": "",
                "unsigned": false,
                "auto_increment": false
            }
        },
        "indexes": {
            "PRIMARY": {
                "type": "primary",
                "name": "PRIMARY",
                "columns": [
                    "id"
                ],
                "length": [
                    null
                ]
            }
        },
        "inserts": [
            {
                "id": "1",
                "name_key": "cat1"
            },
            {
                "id": "2",
                "name_key": "cat2"
            }
        ]
    },
    "vssupport_ticket_action_history": {
        "name": "vssupport_ticket_action_history",
        "columns": {
            "id": {
                "allow_null": false,
                "auto_increment": true,
                "comment": "ID Number",
                "decimals": null,
                "default": null,
                "length": 20,
                "name": "id",
                "type": "BIGINT",
                "unsigned": true,
                "values": []
            },
            "ticket": {
                "allow_null": false,
                "auto_increment": false,
                "comment": "",
                "decimals": null,
                "default": "0",
                "length": 10,
                "name": "ticket",
                "type": "INT",
                "unsigned": true,
                "values": []
            },
            "created": {
                "allow_null": false,
                "auto_increment": false,
                "comment": "",
                "decimals": null,
                "default": "current_timestamp()",
                "length": 0,
                "name": "created",
                "type": "DATETIME",
                "unsigned": false,
                "values": []
            },
            "kind": {
                "allow_null": false,
                "auto_increment": false,
                "comment": "",
                "decimals": null,
                "default": "0",
                "length": 3,
                "name": "kind",
                "type": "TINYINT",
                "unsigned": true,
                "values": []
            },
            "reference_id": {
                "allow_null": true,
                "auto_increment": false,
                "comment": "",
                "decimals": null,
                "default": null,
                "length": 10,
                "name": "reference_id",
                "type": "INT",
                "unsigned": true,
                "values": []
            },
            "initiator": {
                "allow_null": false,
                "auto_increment": false,
                "comment": "",
                "decimals": null,
                "default": "0",
                "length": 10,
                "name": "initiator",
                "type": "INT",
                "unsigned": true,
                "values": []
            }
        },
        "indexes": {
            "PRIMARY": {
                "type": "primary",
                "name": "PRIMARY",
                "length": [
                    null
                ],
                "columns": [
                    "id"
                ]
            },
            "ticket": {
                "type": "key",
                "name": "ticket",
                "length": [
                    null
                ],
                "columns": [
                    "ticket"
                ]
            }
        },
        "collation": "utf8mb4_unicode_ci",
        "inserts": [
            {
                "id": "1",
                "ticket": "1",
                "created": "000-00-00",
                "kind": "1",
                "reference_id": "1",
                "initiator": "1"
            }
        ]
    },
    "vssupport_ticket_stati": {
        "name": "vssupport_ticket_stati",
        "columns": {
            "id": {
                "name": "id",
                "type": "BIGINT",
                "length": "20",
                "decimals": null,
                "values": null,
                "allow_null": false,
                "default": 0,
                "comment": "",
                "unsigned": true,
                "auto_increment": true
            },
            "name_key": {
                "name": "name_key",
                "type": "TINYTEXT",
                "length": null,
                "decimals": null,
                "values": null,
                "allow_null": false,
                "default": null,
                "comment": "",
                "unsigned": false,
                "auto_increment": false
            }
        },
        "indexes": {
            "PRIMARY": {
                "type": "primary",
                "name": "PRIMARY",
                "columns": [
                    "id"
                ],
                "length": [
                    null
                ]
            }
        },
        "inserts": [
            {
                "id": "0",
                "name_key": "open"
            },
            {
                "id": "2",
                "name_key": "processing"
            },
            {
                "id": "5",
                "name_key": "halted"
            },
            {
                "id": "8",
                "name_key": "completed"
            },
            {
                "id": "9",
                "name_key": "wontfix"
            },
            {
                "id": "16",
                "name_key": "custom"
            }
        ]
    }
}